schatsi/__init__.py
schatsi/cli.py
schatsi/jobs/__init__.py
schatsi/jobs/base_job.py
schatsi/jobs/parallel_job.py
schatsi/jobs/single_job.py
schatsi/models/___init__.py
schatsi/models/document.py
schatsi/models/ranking.py
schatsi/processor/document_processor.py
schatsi/processor/ngram_processor.py
schatsi/processor/ranker.py
schatsi/processor/text_cleaner.py
schatsi/reader/__init__.py
schatsi/reader/base_reader.py
schatsi/reader/docx_reader.py
schatsi/reader/pdf_reader.py
schatsi/reader/reader_facade.py
schatsi/reader/reader_type.py
schatsi/reader/xls_reader.py
schatsi/reader/xlsx_reader.py
schatsi-0.1.37.dist-info/METADATA
schatsi-0.1.37.dist-info/WHEEL
schatsi-0.1.37.dist-info/entry_points.txt
schatsi-0.1.37.dist-info/RECORD
